pyfarkle/__init__.py
pyfarkle/__main__.py
pyfarkle/farkle.css
pyfarkle/game.py
pyfarkle/scores.py
pyfarkle/screens.py
pyfarkle/strategy.py
pyfarkle-0.1.dist-info/LICENSE
pyfarkle-0.1.dist-info/METADATA
pyfarkle-0.1.dist-info/WHEEL
pyfarkle-0.1.dist-info/entry_points.txt
pyfarkle-0.1.dist-info/top_level.txt
pyfarkle-0.1.dist-info/zip-safe
pyfarkle-0.1.dist-info/RECORD
